{
  "ConceptModel": {
    "conceptHeading": "Integers",
    "conceptFormula": "1, 2, 3, 4, 5, ...",
    "conceptParagraphs": [
      {
        "paragraphText": "We use <strong class='green'> Integers </strong> every day. Whether it is counting how many candies you got on halloween, or making sure that you have the right number of fingers and toes. Whole Number are incredibly useful and serve as one of the fundamental pillars of Mathematics. Integers are <strong class='blue'> positive </strong> numbers, including zero, without any decimal or fractional parts. They are numbers that represent whole things without pieces.",
        "paragraphImg": "https://cdn-skill.splashmath.com/panel-uploads/GlossaryTerm/4aa1895261a2415385d19d7865d856cf/1547180043_Whole-Numbers-0-1-2-3-4.png",
        "paragraphImgAlt": "Whole Number Line"
      },
      {
        "paragraphText": "We use <strong class='green'> Integers </strong> every day. Whether it is counting how many candies you got on halloween, or making sure that you have the right number of fingers and toes. Whole Number are incredibly useful and serve as one of the fundamental pillars of Mathematics. Integers are <strong class='blue'> positive </strong> numbers, including zero, without any decimal or fractional parts. They are numbers that represent whole things without pieces.",
        "paragraphImg": "",
        "paragraphImgAlt": ""
      }
    ],
    "conceptInteraction": "",
    "conceptImg": ""
  },
  "HistoryViewModel": {
    "historyHeader": "History of Integers",
    "historySections": [
      {
        "sectionHeader":"Animals and Numbers",
        "sectionSubheader": "Mammals and Numbers",
        "sectionIcon": "fas fa-brain",
        "sectionParagraphs": [
          {
            "paragraphHead": "",
            "paragraphText": "Animals are counters. No matter the species, there are animals that count their steps to know how far away from home they are. etc etc. Animals are counters. No matter the species, there are animals that count their steps to know how far away from home they are. etc etc. Animals are counters. No matter the species, there are animals that count their steps to know how far away from home they are. etc etc",
            "paragraphImg": "",
            "imgAlt": ""
          }
        ]
      },
      {
        "sectionHeader":"History of Integers",
        "sectionSubheader": "Early Human History",
        "sectionIcon": "fas fa-monument",
        "sectionParagraphs": [
          {
            "paragraphHead": "",
            "paragraphText": "Animals are counters. No matter the species, there are animals that count their steps to know how far away from home they are. etc etc",
            "paragraphImg": "",
            "imgAlt": ""
          }
        ]
      }
    ]
  },
  "ApplicationViewModel": {
    "applicationHeading": "Application of Integers",
    "applications": [
      {
        "applicationId":0,
        "applicationBackground": "",
        "applicationText": "Integers",
        "applicationModal": {
          "modalHeader": "Integers Whole 'Things'",
          "modalParagraphs": [
            {
              "paragraphText": "",
              "paragraphImage": ""
            }
          ]
        }
      },
      {
        "applicationId":0,
        "applicationBackground": "",
        "applicationText": "Integers",
        "applicationModal": {
          "modalHeader": "Integers Whole 'Things'",
          "modalParagraphs": [
            {
              "paragraphText": "",
              "paragraphImage": ""
            }
          ]
        }
      },
      {
        "applicationId":0,
        "applicationBackground": "",
        "applicationText": "Integers",
        "applicationModal": {
          "modalHeader": "Integers Whole 'Things'",
          "modalParagraphs": [
            {
              "paragraphText": "",
              "paragraphImage": ""
            }
          ]
        }
      },
      {
        "applicationId":0,
        "applicationBackground": "",
        "applicationText": "Integers",
        "applicationModal": {
          "modalHeader": "Integers Whole 'Things'",
          "modalParagraphs": [
            {
              "paragraphText": "",
              "paragraphImage": ""
            }
          ]
        }
      },
      {
        "applicationId":0,
        "applicationBackground": "",
        "applicationText": "Integers",
        "applicationModal": {
          "modalHeader": "Integers Whole 'Things'",
          "modalParagraphs": [
            {
              "paragraphText": "",
              "paragraphImage": ""
            }
          ]
        }
      },
      {
        "applicationId":0,
        "applicationBackground": "",
        "applicationText": "Integers",
        "applicationModal": {
          "modalHeader": "Integers Whole 'Things'",
          "modalParagraphs": [
            {
              "paragraphText": "",
              "paragraphImage": ""
            }
          ]
        }
      }
    ]
  },
  "PracticeViewModel": ""
}
